{"effect_changes":[],"effect_entries":[],"flavor_text_entries":[],"generation":{"name":"generation-ix","url":"https://pokeapi.co/api/v2/generation/9/"},"id":288,"is_main_series":true,"name":"orichalcum-pulse","names":[{"language":{"name":"ja-Hrkt","url":"https://pokeapi.co/api/v2/language/1/"},"name":"ひひいろのこどう"},{"language":{"name":"fr","url":"https://pokeapi.co/api/v2/language/5/"},"name":"Pouls Orichalque"},{"language":{"name":"de","url":"https://pokeapi.co/api/v2/language/6/"},"name":"Orichalkum-Puls"},{"language":{"name":"es","url":"https://pokeapi.co/api/v2/language/7/"},"name":"Latido Oricalco"},{"language":{"name":"it","url":"https://pokeapi.co/api/v2/language/8/"},"name":"Ritmo d’Oricalco"},{"language":{"name":"en","url":"https://pokeapi.co/api/v2/language/9/"},"name":"Orichalcum Pulse"},{"language":{"name":"ja","url":"https://pokeapi.co/api/v2/language/11/"},"name":"ひひいろのこどう"}],"pokemon":[{"is_hidden":false,"pokemon":{"name":"koraidon","url":"https://pokeapi.co/api/v2/pokemon/1007/"},"slot":1},{"is_hidden":true,"pokemon":{"name":"koraidon","url":"https://pokeapi.co/api/v2/pokemon/1007/"},"slot":3},{"is_hidden":false,"pokemon":{"name":"koraidon-limited-build","url":"https://pokeapi.co/api/v2/pokemon/10264/"},"slot":1},{"is_hidden":true,"pokemon":{"name":"koraidon-limited-build","url":"https://pokeapi.co/api/v2/pokemon/10264/"},"slot":3},{"is_hidden":false,"pokemon":{"name":"koraidon-sprinting-build","url":"https://pokeapi.co/api/v2/pokemon/10265/"},"slot":1},{"is_hidden":true,"pokemon":{"name":"koraidon-sprinting-build","url":"https://pokeapi.co/api/v2/pokemon/10265/"},"slot":3},{"is_hidden":false,"pokemon":{"name":"koraidon-swimming-build","url":"https://pokeapi.co/api/v2/pokemon/10266/"},"slot":1},{"is_hidden":true,"pokemon":{"name":"koraidon-swimming-build","url":"https://pokeapi.co/api/v2/pokemon/10266/"},"slot":3},{"is_hidden":false,"pokemon":{"name":"koraidon-gliding-build","url":"https://pokeapi.co/api/v2/pokemon/10267/"},"slot":1},{"is_hidden":true,"pokemon":{"name":"koraidon-gliding-build","url":"https://pokeapi.co/api/v2/pokemon/10267/"},"slot":3}]}
